requirements.txt
setup.py
django_traceback/__init__.py
django_traceback/admin.py
django_traceback/models.py
django_traceback/utils.py
django_traceback.egg-info/PKG-INFO
django_traceback.egg-info/SOURCES.txt
django_traceback.egg-info/dependency_links.txt
django_traceback.egg-info/requires.txt
django_traceback.egg-info/top_level.txt
django_traceback/migrations/0001_initial.py
django_traceback/migrations/__init__.py