Metadata-Version: 2.1
Name: django-traceback
Version: 2020.7.1
Summary: Traceback model and utils
Home-page: https://github.com/andrewp-as-is/django-traceback.py
License: Unlicense
Keywords: django traceback
Platform: UNKNOWN
Classifier: Framework :: Django
Classifier: License :: Public Domain
Classifier: Operating System :: OS Independent
Classifier: Programming Language :: Python :: 3
